ogbench/__init__.py
ogbench/relabel_utils.py
ogbench/utils.py
ogbench/locomaze/__init__.py
ogbench/locomaze/ant.py
ogbench/locomaze/humanoid.py
ogbench/locomaze/maze.py
ogbench/locomaze/point.py
ogbench/locomaze/assets/ant.xml
ogbench/locomaze/assets/humanoid.xml
ogbench/locomaze/assets/point.xml
ogbench/manipspace/__init__.py
ogbench/manipspace/mjcf_utils.py
ogbench/manipspace/viewer_utils.py
ogbench/manipspace/controllers/__init__.py
ogbench/manipspace/controllers/diff_ik.py
ogbench/manipspace/descriptions/button_inner.xml
ogbench/manipspace/descriptions/button_outer.xml
ogbench/manipspace/descriptions/buttons.xml
ogbench/manipspace/descriptions/cube.xml
ogbench/manipspace/descriptions/cube_inner.xml
ogbench/manipspace/descriptions/cube_outer.xml
ogbench/manipspace/descriptions/drawer.xml
ogbench/manipspace/descriptions/floor_wall.xml
ogbench/manipspace/descriptions/window.xml
ogbench/manipspace/descriptions/metaworld/button/button.stl
ogbench/manipspace/descriptions/metaworld/button/buttonring.stl
ogbench/manipspace/descriptions/metaworld/button/metal1.png
ogbench/manipspace/descriptions/metaworld/button/stopbot.stl
ogbench/manipspace/descriptions/metaworld/button/stopbutton.stl
ogbench/manipspace/descriptions/metaworld/button/stopbuttonrim.stl
ogbench/manipspace/descriptions/metaworld/button/stopbuttonrod.stl
ogbench/manipspace/descriptions/metaworld/button/stoptop.stl
ogbench/manipspace/descriptions/metaworld/drawer/drawer.stl
ogbench/manipspace/descriptions/metaworld/drawer/drawercase.stl
ogbench/manipspace/descriptions/metaworld/drawer/drawerhandle.stl
ogbench/manipspace/descriptions/metaworld/window/window_base.stl
ogbench/manipspace/descriptions/metaworld/window/window_frame.stl
ogbench/manipspace/descriptions/metaworld/window/window_h_base.stl
ogbench/manipspace/descriptions/metaworld/window/window_h_frame.stl
ogbench/manipspace/descriptions/metaworld/window/windowa_frame.stl
ogbench/manipspace/descriptions/metaworld/window/windowa_glass.stl
ogbench-1.2.1.dist-info/LICENSE
ogbench-1.2.1.dist-info/WHEEL
ogbench-1.2.1.dist-info/METADATA
ogbench-1.2.1.dist-info/RECORD
